{
    "words": {
        "rapace": {
            "catGram": "adjectif",
            "def": "Avide d'argent, de profit, au détriment d'autrui."
        },
        "bassiner": {
            "catGram": "verbe",
            "def": "Chauffer (un lit) avec une bassinoire."
        },
        "rôdeur": {
            "catGram": "nom",
            "def": "Personne, animal qui rôde."
        },
        "narine": {
            "catGram": "nom féminin",
            "def": "Chacun des deux orifices extérieurs du nez"
        }
    }
}