{
    "words": {
        "serrure": {
            "catGram": "nom féminin",
            "def": "Mécanisme de fermeture actionné par une clé."
        },
        "fermé": {
            "catGram": "adjectif",
            "def": "Qu'on a déplacé de façon à clore, boucher, obstruer une ouverture."
        },
        "ostraciser": {
            "catGram": "verbe",
            "def": "Frapper d'ostracisme."
        },
        "perfidie": {
            "catGram": "nom féminin",
            "def": "Caractère de ce qui est perfide, d'une personne perfide."
        }
    }
}