{
    "words": {
        "destruction": {
            "catGram": "nom féminin",
            "def": "Action de détruire"
        },
        "émanciper": {
            "catGram": "verbe",
            "def": "Affranchir un mineur de l’autorité parentale ou de la tutelle."
        },
        "pervers": {
            "catGram": "adjectif",
            "def": "Enclin au mal"
        },
        "cognée": {
            "catGram": "nom féminin",
            "def": "Grosse hache à biseau étroit généralement utilisée par les bûcherons."
        }
    }
}