{
    "words": {
        "buisson": {
            "catGram": "nom masculin",
            "def": "Bouquet, touffe de végétaux ligneux, sauvages, généralement épineux et rameux."
        },
        "chiffonner": {
            "catGram": "verbe",
            "def": "Froisser (une étoffe, du papier)."
        },
        "abriter": {
            "catGram": "verbe",
            "def": "Mettre, tenir à l'abri."
        },
        "jonc": {
            "catGram": "nom masculin",
            "def": "Plante herbacée des milieux marécageux et humides, dont la tige ronde, droite et souple, semble souvent porter son inflorescence sur le côté."
        }
    }
}