{
    "words": {
        "automatiquement": {
            "catGram": "adverbe",
            "def": "De manière automatique."
        },
        "constitutif": {
            "catGram": "adjectif",
            "def": "Qui entre dans la constitution, dans la composition de qqch."
        },
        "agrémenter": {
            "catGram": "verbe",
            "def": "Rendre plus agréable, donner de l'agrément"
        },
        "pratiquant": {
            "catGram": "adjectif",
            "def": "Qui observe les pratiques de sa religion."
        }
    }
}